vid2emoji/__init__.py
vid2emoji/encode.py
vid2emoji/emojEncode/__init__.py
vid2emoji/emojEncode/emojencoder.py
vid2emoji/emojEncode/emojiGamutPartitioned.json
vid2emoji-0.0.1.dist-info/LICENSE.txt
vid2emoji-0.0.1.dist-info/METADATA
vid2emoji-0.0.1.dist-info/WHEEL
vid2emoji-0.0.1.dist-info/entry_points.txt
vid2emoji-0.0.1.dist-info/top_level.txt
vid2emoji-0.0.1.dist-info/RECORD
