Metadata-Version: 2.1
Name: vid2emoji
Version: 0.0.1
Summary: Convert videos to emoji... videos
Home-page: https://github.com/ryanfox/vid2emoji
Author: Ryan Fox
Author-email: ryan@foxrow.com
License: GPLv3
License-File: LICENSE.txt
Requires-Dist: moviepy (==1.0.3)
Requires-Dist: numpy (==1.22.3)
Requires-Dist: Pillow (==9.1.0)
Requires-Dist: scikit-learn (==1.0.2)
Requires-Dist: tqdm (==4.64.0)
